Fa_bh.v
module Ha_bh(s,c,a,b);
input a,b;
output reg s,c;
always@(a,b)
begin
s=a^b;
c=a&b;
end
endmodule
module Fa_bh(s,c,a,b,cin);
input a,b,cin;
output s,c;
wire n1,n2,n3;
Ha_bh Ha_bh1(n1,n2,a,b);
Ha_bh Ha_bh2(s,n3,n1,cin);
assign c=n3|n2;
endmodule

Internship/Fa_bh_test.v
`timescale 1ns/1ps
module Fa_bh_test;
reg a,b,cin;
wire s,c;
Fa_bh uut(.s(s),.c(c),.a(a),.b(b),.cin(cin));
initial begin
$monitor("s=%b,c=%b,a=%b,b=%b,cin=%b",s,c,a,b,cin);
end 
initial 
begin
#10 a=0;b=0;cin=0;
#10 a=0;b=0;cin=1;
#10 a=0;b=1;cin=0;
#10 a=0;b=1;cin=1;
#10 a=1;b=0;cin=0;
#10 a=1;b=0;cin=1;
#10 a=1;b=1;cin=0;
#10 a=1;b=1;cin=1;
end
initial begin
$dumpfile("Fawave.vcd");
$dumpvars();
end 
endmodule

Fawave.vcd
$date
	Thu Jun  5 06:38:22 2025
$end
$version
	Icarus Verilog
$end
$timescale
	1ps
$end
$scope module Fa_bh_test $end
$var wire 1 ! s $end
$var wire 1 " c $end
$var reg 1 # a $end
$var reg 1 $ b $end
$var reg 1 % cin $end
$scope module uut $end
$var wire 1 # a $end
$var wire 1 $ b $end
$var wire 1 " c $end
$var wire 1 % cin $end
$var wire 1 ! s $end
$var wire 1 & n3 $end
$var wire 1 ' n2 $end
$var wire 1 ( n1 $end
$scope module Ha_bh1 $end
$var wire 1 # a $end
$var wire 1 $ b $end
$var reg 1 ' c $end
$var reg 1 ( s $end
$upscope $end
$scope module Ha_bh2 $end
$var wire 1 ( a $end
$var wire 1 % b $end
$var reg 1 & c $end
$var reg 1 ! s $end
$upscope $end
$upscope $end
$upscope $end
$enddefinitions $end
$comment Show the parameter values. $end
$dumpall
$end
#0
$dumpvars
x(
x'
x&
x%
x$
x#
x"
x!
$end
#10000
0"
0&
0!
0'
0(
0%
0$
0#
#20000
1!
1%
#30000
1(
0%
1$
#40000
1"
1&
0!
1%
#50000
0"
0&
1!
0%
0$
1#
#60000
1"
1&
0!
1%
#70000
0&
1'
0(
0%
1$
#80000
1!
1%
