Neg_latch.v
module Neg_latch(clk,rst,q,d);
    input clk,rst,d;
    output reg q;
    always@(*)
    begin
        if(rst)
            q<=1'b0;
        else if(!clk)
            q<=d;
    end
endmodule

RTL/Internship/Neg_latch_test.v
`timescale 1ns/1ps

module Neg_latch_test;

  reg d, clk, rst;
  wire q;

  Neg_latch uut (.q(q), .d(d), .clk(clk), .rst(rst));

  initial begin
    clk = 0;
    forever #5 clk = ~clk;
  end
    initial begin
    $dumpfile("Negwave.vcd");
    $dumpvars();
  end

  initial begin
    $monitor("Time=%0t, q=%b, d=%b, clk=%b, rst=%b", $time, q, d, clk, rst);

    d = 0; rst = 1;
    #12 rst = 0; d = 1;
    #10 d = 0;
    #10 d = 1;
    #10 rst = 1;
    #5  rst = 0;
    #10 d = 0;
    #10 $finish;
  end

endmodule

Negwave.vcd
$date
	Fri Jun  6 11:09:32 2025
$end
$version
	Icarus Verilog
$end
$timescale
	1ps
$end
$scope module Neg_latch_test $end
$var wire 1 ! q $end
$var reg 1 " clk $end
$var reg 1 # d $end
$var reg 1 $ rst $end
$scope module uut $end
$var wire 1 " clk $end
$var wire 1 # d $end
$var wire 1 $ rst $end
$var reg 1 ! q $end
$upscope $end
$upscope $end
$enddefinitions $end
$comment Show the parameter values. $end
$dumpall
$end
#0
$dumpvars
1$
0#
0"
0!
$end
#5000
1"
#10000
0"
#12000
1!
1#
0$
#15000
1"
#20000
0"
#22000
0!
0#
#25000
1"
#30000
0"
#32000
1!
1#
#35000
1"
#40000
0"
#42000
0!
1$
#45000
1"
#47000
0$
#50000
1!
0"
#55000
1"
#57000
0#
#60000
0!
0"
