Fir_filter/Fir_filter.v
module Fir_filter(
    input clk,
    input rst,
    input [7:0]x_in,
    output reg [15:0]y_out
);
parameter N=4;
wire [7:0] coeff [0:N-1];
assign coeff[0] = 8'd1;
assign coeff[1] = 8'd2;
assign coeff[2] = 8'd3;
assign coeff[3] = 8'd4;
integer i;
reg [7:0] x_reg [0:N-1];
always @(posedge clk or posedge rst) begin
    if(rst)
    begin 
        for(i=0;i<N;i=1+i)
        begin
            x_reg[i]<=8'd0;
        end
        y_out <=16'd0;
    end 
    else 
    begin
        for(i=N-1;i>0;i=i-1)
        begin
            x_reg[i]<= x_reg[i-1];
        end
        x_reg[0] <= x_in;
        y_out <= (x_reg[0] * coeff[0]) + 
                  (x_reg[1] * coeff[1]) + 
                  (x_reg[2] * coeff[2]) + 
                  (x_reg[3] * coeff[3]);
        end
    end
endmodule

Fir_filter/tb_fir_filter.v
module tb_fir_filter;
    reg clk, rst;
    reg [7:0] x_in;
    wire [15:0] y_out;

    Fir_filter dut (
        .clk(clk),
        .rst(rst),
        .x_in(x_in),
        .y_out(y_out)
    );

    always #5 clk = ~clk;

    initial begin
        $display("Time\tclk\tx_in\ty_out");
        $monitor("%0t\t%b\t%d\t%d", $time, clk, x_in, y_out);

        clk = 0;
        rst = 1;
        x_in = 0;

        #10 rst = 0;

        x_in = 8'd1; #10;
        x_in = 8'd2; #10;
        x_in = 8'd3; #10;
        x_in = 8'd4; #10;
        x_in = 8'd5; #10;
        x_in = 8'd6; #10;
        x_in = 8'd0; #20;

        $finish;
    end
    initial begin
        $dumpfile("tb_fir_filter.vcd");
        $dumpvars(0, tb_fir_filter);
    end
endmodule

Fir_filter/tb_fir_filter.vcd
$date
	Wed Jul 23 12:01:48 2025
$end
$version
	Icarus Verilog
$end
$timescale
	1s
$end
$scope module tb_fir_filter $end
$var wire 16 ! y_out [15:0] $end
$var reg 1 " clk $end
$var reg 1 # rst $end
$var reg 8 $ x_in [7:0] $end
$scope module dut $end
$var wire 1 " clk $end
$var wire 1 # rst $end
$var wire 8 % x_in [7:0] $end
$var parameter 32 & N $end
$var reg 16 ' y_out [15:0] $end
$var integer 32 ( i [31:0] $end
$upscope $end
$upscope $end
$enddefinitions $end
$comment Show the parameter values. $end
$dumpall
b100 &
$end
#0
$dumpvars
b100 (
b0 '
b0 %
b0 $
1#
0"
b0 !
$end
#5
b100 (
1"
#10
0"
b1 $
b1 %
0#
#15
b0 (
1"
#20
0"
b10 $
b10 %
#25
b1 !
b1 '
b0 (
1"
#30
0"
b11 $
b11 %
#35
b100 !
b100 '
b0 (
1"
#40
0"
b100 $
b100 %
#45
b1010 !
b1010 '
b0 (
1"
#50
0"
b101 $
b101 %
#55
b10100 !
b10100 '
b0 (
1"
#60
0"
b110 $
b110 %
#65
b11110 !
b11110 '
b0 (
1"
#70
0"
b0 $
b0 %
#75
b101000 !
b101000 '
b0 (
1"
#80
0"
#85
b101011 !
b101011 '
b0 (
1"
