Washin_machine/Washing_machine.v
module Washing_machine(
    input clk,
    input rst,
    input srt,
    output reg fill,
    output reg wash,
    output reg rinse,
    output reg spin,
    output reg done,
    output reg red,
    output reg green,
    output reg buzzer
);

    // FSM State Definitions
    reg [2:0] current_state, next_state;
    parameter Idle  = 3'b000,
              Fill  = 3'b001,
              Wash  = 3'b010,
              Rinse = 3'b011,
              Spin  = 3'b100,
              Done  = 3'b101;

    // Timer Register
    reg [3:0] timer; // 4-bit timer (max 15)

    // Duration for each stage (in clock cycles)
    parameter TIME_FILL  = 4,
              TIME_WASH  = 4,
              TIME_RINSE = 4,
              TIME_SPIN  = 4;

    // FSM state update
    always @(posedge clk or posedge rst) begin
        if (rst)
            current_state <= Idle;
        else
            current_state <= next_state;
    end

    // Timer control logic
    always @(posedge clk or posedge rst) begin
        if (rst)
            timer <= 0;
        else if (current_state == Idle)
            timer <= 0;
        else if (timer < 15)
            timer <= timer + 1;
        else
            timer <= 0;
    end

    // Next state logic and output control
    always @(*) begin
        // Default outputs
        fill = 0;
        wash = 0;
        rinse = 0;
        spin = 0;
        done = 0;
        red = 0;
        green = 0;
        buzzer = 0;
        next_state = current_state;

        case (current_state)
            Idle: begin
                if (srt)
                    next_state = Fill;
            end

            Fill: begin
                fill = 1;
                red = 1;
                if (timer == TIME_FILL)
                    next_state = Wash;
            end

            Wash: begin
                wash = 1;
                red = 1;
                if (timer == TIME_WASH)
                    next_state = Rinse;
            end

            Rinse: begin
                rinse = 1;
                red = 1;
                if (timer == TIME_RINSE)
                    next_state = Spin;
            end

            Spin: begin
                spin = 1;
                red = 1;
                if (timer == TIME_SPIN)
                    next_state = Done;
            end

            Done: begin
                red = 0;
                done = 1;
                green = 1;
                buzzer = 1;
                next_state = Idle; // Optional: restart cycle
            end

            default: next_state = Idle;
        endcase
    end

endmodule

Washin_machine/Washing_machine_tb.v
`timescale 1ns / 1ps

module Washing_machine_tb;

    reg clk = 0;
    reg rst = 0;
    reg srt = 0;

    wire fill, wash, rinse, spin, done, red, green, buzzer;

    Washing_machine dut (
        .clk(clk),
        .rst(rst),
        .srt(srt),
        .fill(fill),
        .wash(wash),
        .rinse(rinse),
        .spin(spin),
        .done(done),
        .red(red),
        .green(green),
        .buzzer(buzzer)
    );

    always #5 clk = ~clk;

    initial begin
        $dumpfile("washing_machine.vcd");
        $dumpvars(0, Washing_machine_tb);

        rst = 1;
        #10 rst = 0;
        #10 srt = 1;
        #10 srt = 0;

        #2000 $finish;
    end

endmodule

Washin_machine/washing_machine.vcd
$date
	Tue Jul 01 12:19:58 2025
$end
$version
	Icarus Verilog
$end
$timescale
	1ps
$end
$scope module Washing_machine_tb $end
$var wire 1 ! wash $end
$var wire 1 " spin $end
$var wire 1 # rinse $end
$var wire 1 $ red $end
$var wire 1 % green $end
$var wire 1 & fill $end
$var wire 1 ' done $end
$var wire 1 ( buzzer $end
$var reg 1 ) clk $end
$var reg 1 * rst $end
$var reg 1 + srt $end
$scope module dut $end
$var wire 1 ) clk $end
$var wire 1 * rst $end
$var wire 1 + srt $end
$var parameter 3 , Done $end
$var parameter 3 - Fill $end
$var parameter 3 . Idle $end
$var parameter 3 / Rinse $end
$var parameter 3 0 Spin $end
$var parameter 32 1 TIME_FILL $end
$var parameter 32 2 TIME_RINSE $end
$var parameter 32 3 TIME_SPIN $end
$var parameter 32 4 TIME_WASH $end
$var parameter 3 5 Wash $end
$var reg 1 ( buzzer $end
$var reg 3 6 current_state [2:0] $end
$var reg 1 ' done $end
$var reg 1 & fill $end
$var reg 1 % green $end
$var reg 3 7 next_state [2:0] $end
$var reg 1 $ red $end
$var reg 1 # rinse $end
$var reg 1 " spin $end
$var reg 4 8 timer [3:0] $end
$var reg 1 ! wash $end
$upscope $end
$upscope $end
$enddefinitions $end
$comment Show the parameter values. $end
$dumpall
b10 5
b100 4
b100 3
b100 2
b100 1
b100 0
b11 /
b0 .
b1 -
b101 ,
$end
#0
$dumpvars
b0 8
b0 7
b0 6
0+
1*
0)
0(
0'
0&
0%
0$
0#
0"
0!
$end
#5000
1)
#10000
0)
0*
#15000
1)
#20000
b1 7
0)
1+
#25000
1$
1&
b1 6
1)
#30000
1$
1&
0)
0+
#35000
1$
1&
b1 8
1)
#40000
0)
#45000
1$
1&
b10 8
1)
#50000
0)
#55000
1$
1&
b11 8
1)
#60000
0)
#65000
b10 7
1$
1&
b100 8
1)
#70000
0)
#75000
1!
1$
0&
b10 6
b101 8
1)
#80000
0)
#85000
1$
1!
b110 8
1)
#90000
0)
#95000
1$
1!
b111 8
1)
#100000
0)
#105000
1$
1!
b1000 8
1)
#110000
0)
#115000
1$
1!
b1001 8
1)
#120000
0)
#125000
1$
1!
b1010 8
1)
#130000
0)
#135000
1$
1!
b1011 8
1)
#140000
0)
#145000
1$
1!
b1100 8
1)
#150000
0)
#155000
1$
1!
b1101 8
1)
#160000
0)
#165000
1$
1!
b1110 8
1)
#170000
0)
#175000
1$
1!
b1111 8
1)
#180000
0)
#185000
1$
1!
b0 8
1)
#190000
0)
#195000
1$
1!
b1 8
1)
#200000
0)
#205000
1$
1!
b10 8
1)
#210000
0)
#215000
1$
1!
b11 8
1)
#220000
0)
#225000
b11 7
1$
1!
b100 8
1)
#230000
0)
#235000
1#
1$
0!
b11 6
b101 8
1)
#240000
0)
#245000
1$
1#
b110 8
1)
#250000
0)
#255000
1$
1#
b111 8
1)
#260000
0)
#265000
1$
1#
b1000 8
1)
#270000
0)
#275000
1$
1#
b1001 8
1)
#280000
0)
#285000
1$
1#
b1010 8
1)
#290000
0)
#295000
1$
1#
b1011 8
1)
#300000
0)
#305000
1$
1#
b1100 8
1)
#310000
0)
#315000
1$
1#
b1101 8
1)
#320000
0)
#325000
1$
1#
b1110 8
1)
#330000
0)
#335000
1$
1#
b1111 8
1)
#340000
0)
#345000
1$
1#
b0 8
1)
#350000
0)
#355000
1$
1#
b1 8
1)
#360000
0)
#365000
1$
1#
b10 8
1)
#370000
0)
#375000
1$
1#
b11 8
1)
#380000
0)
#385000
b100 7
1$
1#
b100 8
1)
#390000
0)
#395000
1"
1$
0#
b100 6
b101 8
1)
#400000
0)
#405000
1$
1"
b110 8
1)
#410000
0)
#415000
1$
1"
b111 8
1)
#420000
0)
#425000
1$
1"
b1000 8
1)
#430000
0)
#435000
1$
1"
b1001 8
1)
#440000
0)
#445000
1$
1"
b1010 8
1)
#450000
0)
#455000
1$
1"
b1011 8
1)
#460000
0)
#465000
1$
1"
b1100 8
1)
#470000
0)
#475000
1$
1"
b1101 8
1)
#480000
0)
#485000
1$
1"
b1110 8
1)
#490000
0)
#495000
1$
1"
b1111 8
1)
#500000
0)
#505000
1$
1"
b0 8
1)
#510000
0)
#515000
1$
1"
b1 8
1)
#520000
0)
#525000
1$
1"
b10 8
1)
#530000
0)
#535000
1$
1"
b11 8
1)
#540000
0)
#545000
b101 7
1$
1"
b100 8
1)
#550000
0)
#555000
b0 7
1(
1%
1'
0$
0"
b101 6
b101 8
1)
#560000
0)
#565000
0(
0%
0'
b110 8
b0 6
1)
#570000
0)
#575000
b0 8
1)
